{"id:": "/div[1]", "tag": "div", "attributes": {"type": "article", "{http://www.w3.org/XML/1998/namespace}id": "MG-1678-09_193", "resp": "mercure"}, "children": [{"id": "/div[1]/head[1]", "tag": "head", "children": [{"id": "/div[1]/head[1]/text()[1]", "text": "[Portraits de Leurs Majestés gravez par Mademoiselle Masson]*"}]}, {"id": "/div[1]/bibl[1]", "tag": "bibl", "children": [{"id": "/div[1]/bibl[1]/title[1]", "tag": "title", "children": [{"id": "/div[1]/bibl[1]/title[1]/text()[1]", "text": "Mercure galant"}]}, {"id": "/div[1]/bibl[1]/text()[1]", "text": ", septembre 1678 [tome 9], p. 193."}]}, {"id": "/div[1]/p[1]", "tag": "p", "children": [{"id": "/div[1]/p[1]/text()[1]", "text": "Mademoiselle Masson la suit de pres dans ce merveilleux talent. Elle a gravé les Portraits de Leurs Majestez avec une si entiere ressemblance, qu’aucun trait n’y est oublié. J’ay appris qu’elle travailloit presentement à ceux de Leurs Altesses Royales."}]}]}